openai_image_gen_edit/__init__.py
openai_image_gen_edit/app.py
openai_image_gen_edit/cli.py
openai_image_gen_edit-0.1.8.dist-info/METADATA
openai_image_gen_edit-0.1.8.dist-info/WHEEL
openai_image_gen_edit-0.1.8.dist-info/entry_points.txt
openai_image_gen_edit-0.1.8.dist-info/licenses/LICENSE
openai_image_gen_edit-0.1.8.dist-info/RECORD
